backupctl/__init__.py
backupctl/__main__.py
backupctl/_version.py
backupctl/cli.py
backupctl/constants.py
backupctl/enable_disable/__init__.py
backupctl/enable_disable/_core.py
backupctl/enable_disable/cmd.py
backupctl/inspect/__init__.py
backupctl/inspect/_core.py
backupctl/inspect/cmd.py
backupctl/list/__init__.py
backupctl/list/_core.py
backupctl/list/cmd.py
backupctl/models/filesystem.py
backupctl/models/plan_config.py
backupctl/models/registry.py
backupctl/models/rsync.py
backupctl/models/user_config.py
backupctl/register/__init__.py
backupctl/register/_core.py
backupctl/register/cmd.py
backupctl/remove/__init__.py
backupctl/remove/_core.py
backupctl/remove/cmd.py
backupctl/run/__init__.py
backupctl/run/_core.py
backupctl/run/cmd.py
backupctl/status/__init__.py
backupctl/status/_core.py
backupctl/status/cmd.py
backupctl/utils/cron.py
backupctl/utils/dataclass.py
backupctl/utils/exceptions.py
backupctl/utils/rsync.py
backupctl/utils/schedule.py
backupctl/utils/version.py
backupctl/validate/__init__.py
backupctl/validate/_core.py
backupctl/validate/cmd.py
backupctl-0.1.4.dist-info/METADATA
backupctl-0.1.4.dist-info/WHEEL
backupctl-0.1.4.dist-info/entry_points.txt
backupctl-0.1.4.dist-info/top_level.txt
backupctl-0.1.4.dist-info/RECORD
