Metadata-Version: 2.4
Name: backupctl
Version: 0.1.4
Summary: Declarative rsync-based backup automation tool
Author-email: lmriccardo <rlmarca.dev@gmail.com>
License: MIT
Project-URL: Homepage, https://github.com/lmriccardo/rsync_backup_planner
Project-URL: Repository, https://github.com/lmriccardo/rsync_backup_planner
Project-URL: Issues, https://github.com/lmriccardo/rsync_backup_planner/issues
Project-URL: Changelog, https://github.com/lmriccardo/rsync_backup_planner/releases
Keywords: backup,rsync,automation,cron,nas
Classifier: Development Status :: 3 - Alpha
Classifier: Intended Audience :: System Administrators
Classifier: Topic :: System :: Archiving :: Backup
Classifier: License :: OSI Approved :: MIT License
Classifier: Programming Language :: Python :: 3
Classifier: Programming Language :: Python :: 3.10
Classifier: Programming Language :: Python :: 3.11
Classifier: Programming Language :: Python :: 3.12
Classifier: Operating System :: POSIX :: Linux
Requires-Python: >=3.12
Requires-Dist: pydantic[email]>=2.6
Requires-Dist: croniter>=2.0
Requires-Dist: PyYAML>=6.0
Requires-Dist: tabulate>=0.9
Requires-Dist: requests>=2.32
